code_analyzer/__init__.py
code_analyzer/code_analyzer.py
code_analyzer/code_analyzer_printer.py
code_analyzer/constants.py
code_analyzer/container_comment.py
code_analyzer/exception.py
code_analyzer/interpretable.py
code_analyzer/py.typed
code_analyzer/scope.py
code_analyzer/trace_call_result.py
python_code_analyzer-1.0.14.dist-info/LICENSE
python_code_analyzer-1.0.14.dist-info/METADATA
python_code_analyzer-1.0.14.dist-info/WHEEL
python_code_analyzer-1.0.14.dist-info/top_level.txt
python_code_analyzer-1.0.14.dist-info/RECORD
