Metadata-Version: 2.1
Name: python-code-analyzer
Version: 1.0.14
Summary: A python code analyzer that high jacks the current settrace function to analyze executed code.
Home-page: https://github.com/josephedradan/code_analyzer
Author: Joseph Edradan
Author-email: edradanjoseph245@gmail.com
License: MIT
Keywords: python,analyzer,debugger,python code analyzer,python analyzer
Classifier: Development Status :: 5 - Production/Stable
Classifier: Intended Audience :: Developers
Classifier: License :: OSI Approved :: MIT License
Classifier: Operating System :: MacOS :: MacOS X
Classifier: Operating System :: Microsoft :: Windows
Classifier: Operating System :: Unix
Classifier: Programming Language :: Python :: 3.7
Classifier: Programming Language :: Python :: 3.8
Classifier: Programming Language :: Python :: 3.9
Classifier: Programming Language :: Python :: 3.10
Classifier: Programming Language :: Python :: 3.11
Requires-Python: >=3.7
License-File: LICENSE
Requires-Dist: colorama
Requires-Dist: pandas
Requires-Dist: rich
